cexpay/__init__.py
cexpay/api/__init__.py
cexpay/api/security.py
cexpay/api/v2.py
cexpay-2.0.7.dist-info/LICENSE
cexpay-2.0.7.dist-info/METADATA
cexpay-2.0.7.dist-info/WHEEL
cexpay-2.0.7.dist-info/top_level.txt
cexpay-2.0.7.dist-info/RECORD
